hex_htmltoimg/__init__.py
hex_htmltoimg/hex_htmltoimg.py
hex_htmltoimg-1.2.0.dist-info/METADATA
hex_htmltoimg-1.2.0.dist-info/WHEEL
hex_htmltoimg-1.2.0.dist-info/top_level.txt
hex_htmltoimg-1.2.0.dist-info/RECORD
