Metadata-Version: 2.1
Name: hex_htmltoimg
Version: 1.2.0
Summary: A module to generate images from HTML content
Home-page: https://github.com/yourusername/hex_htmltoimg
Author: azharbhat-dev
Author-email: bazhar691@gmail.com
Classifier: Programming Language :: Python :: 3
Classifier: License :: OSI Approved :: MIT License
Classifier: Operating System :: OS Independent
Requires-Python: >=3.6
Requires-Dist: html2image
Requires-Dist: Pillow
